<?xml version="1.0" encoding="UTF-8"?>

<doctrine-mapping xmlns="http://doctrine-project.org/schemas/orm/doctrine-mapping">

    <entity name="AppBundle\Entity\Supplier" table="app_supplier">
        <id name="id" column="id" type="integer">
            <generator strategy="AUTO" />
        </id>

        <field name="code" column="code" type="string" unique="true" />
        <field name="name" column="name" type="string" />
        <field name="status" column="status" type="string" />

        <one-to-many
            field="products"
            target-entity="AppBundle\Entity\Product"
            mapped-by="supplier">
        </one-to-many>
    </entity>

</doctrine-mapping>
